PACMANCharge/__init__.py
PACMANCharge/atom_init.json
PACMANCharge/pmcharge.py
run/__init__.py
run/run_test.py
run/test.py
PACMAN_charge-1.3.9.dist-info/LICENSE
PACMAN_charge-1.3.9.dist-info/METADATA
PACMAN_charge-1.3.9.dist-info/WHEEL
PACMAN_charge-1.3.9.dist-info/top_level.txt
PACMAN_charge-1.3.9.dist-info/RECORD
